caidao/.gitignore
caidao/__init__.py
caidao/agent.py
caidao/archive.bat
caidao/cn_stopwords.txt
caidao/cn_userdict_hairstyles.txt
caidao/database_router.py
caidao/deploy.bat
caidao/helper_chrome_driver.py
caidao/helper_cmd.py
caidao/helper_copy_tpl.py
caidao/helper_driver.py
caidao/helper_driver_chrome.py
caidao/helper_driver_edge.py
caidao/helper_hash.py
caidao/helper_icmp.py
caidao/helper_img_cmp.py
caidao/helper_net.py
caidao/helper_ocr.py
caidao/helper_pdf.py
caidao/helper_trainer.py
caidao/helper_trans.py
caidao/helper_vector.py
caidao/helper_video.py
caidao/helper_win32.py
caidao/pull.bat
caidao/push.bat
caidao/requirements.txt
caidao/t.py
caidao/test_split_zeros.bin
caidao/tool_cmd.py
caidao/tool_cut.py
caidao/tool_date.py
caidao/tool_dict.py
caidao/tool_doubao.py
caidao/tool_env.py
caidao/tool_ffmpeg.py
caidao/tool_file.py
caidao/tool_gzip.py
caidao/tool_img.py
caidao/tool_img_compare.py
caidao/tool_mall_pdd.py
caidao/tool_numpy.py
caidao/tool_ocr.py
caidao/tool_pandas.py
caidao/tool_prob.py
caidao/tool_re.py
caidao/tool_rect.py
caidao/tool_section.py
caidao/tool_small_red_book.py
caidao/tool_split.py
caidao/tool_static.py
caidao/tool_time.py
caidao/tool_url.py
caidao/tool_user.py
caidao/tool_video.py
caidao/tool_wx.py
caidao/tool_wx_mini_program.py
caidao/adb_tools/__init__.py
caidao/adb_tools/helper_adb.py
caidao/adb_tools/icon_wx2adb.png
caidao/adb_tools/icon_wxadb.png
caidao/adb_tools/tool_devices.py
caidao/adb_tools/tool_xpath.py
caidao/adb_tools/weixin.py
caidao/adb_tools/common/__init__.py
caidao/adb_tools/common/constants.py
caidao/adb_tools/common/exceptions.py
caidao/adb_tools/common/utils.py
caidao/caidao_tools/__init__.py
caidao/caidao_tools/django/__init__.py
caidao/caidao_tools/django/abstract.py
caidao/caidao_tools/django/base_admin.py
caidao/caidao_tools/django/chat_models.py
caidao/caidao_tools/django/helper_sqlite.py
caidao/caidao_tools/django/kangyang_models.py
caidao/caidao_tools/django/storage.py
caidao-1.0.0.dist-info/METADATA
caidao-1.0.0.dist-info/WHEEL
caidao-1.0.0.dist-info/licenses/LICENSE
caidao-1.0.0.dist-info/RECORD
