Metadata-Version: 2.3
Name: caidao
Version: 1.0.0
Summary: handy tools
Project-URL: Homepage, https://github.com/winstonzhong/caidao
Author-email: winstonzhong <lovekarri@hotmail.com>
License:                                  Apache License
Classifier: License :: OSI Approved :: MIT License
Classifier: Operating System :: OS Independent
Classifier: Programming Language :: Python :: 3
Requires-Python: >=3.6
Requires-Dist: requests==2.13.0
